CalculatorTuringAjdin.py
__init__.py
CalculatorTuringAjdin_AjdinSalihovic-0.0.4.dist-info/LICENSE
CalculatorTuringAjdin_AjdinSalihovic-0.0.4.dist-info/METADATA
CalculatorTuringAjdin_AjdinSalihovic-0.0.4.dist-info/WHEEL
CalculatorTuringAjdin_AjdinSalihovic-0.0.4.dist-info/top_level.txt
CalculatorTuringAjdin_AjdinSalihovic-0.0.4.dist-info/RECORD
