Metadata-Version: 2.1
Name: CalculatorTuringAjdin-AjdinSalihovic
Version: 0.0.4
Summary: Python calculator for Turing college
Author-email: Ajdin Salihovic <ajdin-salihovic@outlook.com>
License: MIT
License-File: LICENSE
